castor_pollux/__init__.py
castor_pollux/adapter.py
castor_pollux/rest.py
castor_pollux-0.0.15.dist-info/licenses/LICENSE
castor_pollux-0.0.15.dist-info/METADATA
castor_pollux-0.0.15.dist-info/WHEEL
castor_pollux-0.0.15.dist-info/top_level.txt
castor_pollux-0.0.15.dist-info/RECORD
