Metadata-Version: 2.4
Name: castor-pollux
Version: 0.0.15
Summary: A library for 'gemini' languagemodels without unnecessary dependencies.
Author-email: Alexander Fedotov <alex.fedotov@aol.com>
Project-URL: Homepage, https://github.com/alxfed/castor-pollux
Project-URL: Bug Tracker, https://github.com/alxfed/castor-pollux/issues
Classifier: Programming Language :: Python :: 3
Classifier: License :: OSI Approved :: MIT License
Classifier: Operating System :: OS Independent
Requires-Python: >=3.10
License-File: LICENSE
Requires-Dist: requests>=2.32.3
Requires-Dist: PyYAML>=6.0.0
Provides-Extra: gemini-google
Requires-Dist: google-genai>=1.11.0; extra == "gemini-google"
Dynamic: license-file
